setup.py
metastruct/__init__.py
metastruct.egg-info/PKG-INFO
metastruct.egg-info/SOURCES.txt
metastruct.egg-info/dependency_links.txt
metastruct.egg-info/top_level.txt
test/test_metastruct.py