Metadata-Version: 1.0
Name: metastruct
Version: 0.0.1
Summary: Just another library.
Home-page: https://github.com/sholsapp/metastruct
Author: Stephen Holsapple
Author-email: sholsapp@gmail.com
License: UNKNOWN
Platform: UNKNOWN
